recommenderhsw/__init__.py
recommenderhsw/recommenderhsw.py
recommenderhsw/data/user_df.csv
recommenderhsw-1.6.dist-info/LICENSE
recommenderhsw-1.6.dist-info/METADATA
recommenderhsw-1.6.dist-info/WHEEL
recommenderhsw-1.6.dist-info/top_level.txt
recommenderhsw-1.6.dist-info/RECORD
